README
setup.py
src/django_mysql_pymysql.egg-info/PKG-INFO
src/django_mysql_pymysql.egg-info/SOURCES.txt
src/django_mysql_pymysql.egg-info/dependency_links.txt
src/django_mysql_pymysql.egg-info/top_level.txt
src/mysql_pymysql/__init__.py
src/mysql_pymysql/base.py
src/mysql_pymysql/introspection.py
src/mysql_pymysql/py3.py