Metadata-Version: 1.0
Name: django-mysql-pymysql
Version: 0.1
Summary: Django MySQL backend for PyMySQL adapter
Home-page: https://github.com/clelland/django-mysql-pymysql
Author: Ian Clelland
Author-email: clelland@gmail.com
License: BSD
Keywords: django mysql pymysql
Platform: UNKNOWN
Classifier: Development Status :: 4 - Beta
Classifier: Framework :: Django
Classifier: Intended Audience :: Developers
Classifier: License :: OSI Approved :: BSD License
Classifier: Operating System :: OS Independent
Classifier: Programming Language :: Python
Classifier: Programming Language :: Python :: 2
Classifier: Programming Language :: Python :: 2.5
Classifier: Programming Language :: Python :: 2.6
Classifier: Programming Language :: Python :: 2.7
Classifier: Programming Language :: Python :: 3
Classifier: Programming Language :: Python :: 3.2
Classifier: Programming Language :: Python :: 3.3
Classifier: Topic :: Database :: Front-Ends
